orpc.py
orpc-0.1.3.dist-info/LICENSE
orpc-0.1.3.dist-info/METADATA
orpc-0.1.3.dist-info/WHEEL
orpc-0.1.3.dist-info/entry_points.txt
orpc-0.1.3.dist-info/top_level.txt
orpc-0.1.3.dist-info/RECORD
