Metadata-Version: 2.1
Name: orpc
Version: 0.1.3
Summary: Open RPC.
Home-page: UNKNOWN
Author: zencore
Author-email: dobetter@zencore.cn
License: MIT
Keywords: orpc,rpc,orpcd,NStreamExchangeProtocolBase
Platform: UNKNOWN
Classifier: Development Status :: 5 - Production/Stable
Classifier: Intended Audience :: Developers
Classifier: Topic :: Software Development :: Libraries :: Python Modules
Classifier: License :: OSI Approved :: MIT License
Classifier: Programming Language :: Python :: 3
Classifier: Programming Language :: Python :: 3 :: Only
License-File: LICENSE
Requires-Dist: daemon-application (>=0.5.9)
Requires-Dist: zenutils (>=0.3.19)
Requires-Dist: orpc-client (>=0.1.3)
Requires-Dist: msgpack
Requires-Dist: gevent
